metronome_loop/__init__.py
metronome_loop/metronome_loop.py
metronome_loop-0.1.0.dist-info/LICENSE
metronome_loop-0.1.0.dist-info/METADATA
metronome_loop-0.1.0.dist-info/WHEEL
metronome_loop-0.1.0.dist-info/top_level.txt
metronome_loop-0.1.0.dist-info/RECORD
