Metadata-Version: 2.1
Name: metronome-loop
Version: 0.1.0
Summary: Library for easy timing without time.sleep()
Home-page: https://github.com/JakubAndrysek/metronome_loop
Author: Jakub Andrýsek
Author-email: email@kubaandrysek.cz
License: MIT
Keywords: metronome_loop,loop,sleep,time
Platform: UNKNOWN
Classifier: Programming Language :: Python :: 3
Classifier: License :: OSI Approved :: MIT License
Classifier: Operating System :: OS Independent
Requires-Python: >=3.6
